{
  "collectionName": "components_blocks_banners",
  "info": {
    "displayName": "Banner",
    "description": ""
  },
  "options": {},
  "attributes": {
    "title": {
      "type": "string"
    },
    "description": {
      "type": "text"
    },
    "divider": {
      "type": "boolean",
      "default": false
    },
    "background": {
      "type": "customField",
      "customField": "plugin::color-picker.color",
      "regex": "^#([A-Fa-f0-9]{6}|[A-Fa-f0-9]{3})$"
    },
    "cards": {
      "type": "component",
      "component": "blocks.text-image",
      "repeatable": true
    }
  }
}
